{
    "pluginStatus": true,
    "isPaid": true,
    "communityName": "South Coast Roleplay",
    "betaCommunity": false,
    "features": {
        "inGameInterface": true,
        "rangeSimulation": true,
        "emergencyHotline": true
    },
    "talkAroundRange": 1500,
    "betaServerGroups": [""],
    "dispatchServerGroups": ["425", "485", "438"],
    "dispatchAdvancedServerGroups": ["304"],
    "dispatchNameTags": [
        "(P)",
        "(S)",
        "(T)",
        "(FIRE)",
        "(QA)",
        "(EVAL)",
        "(911)",
        "(TAC)",
        "(SA)",
        "[911]",
        "[SA]",
        "[TAC]",
        "[P]",
        "[S]",
        "[T]",
        "[FIRE]",
        "[QA]",
        "[EVAL]"
    ],
    "civilianServerGroups": ["437", "428", "429", "430"],
    "civChannels": [34, 289],
    "radioSystems": [23, 281],
    "rtoChannels": [411, 287],
    "radioChannels": [
        {
            "id": 1,
            "name": "Statewide Frequency",
            "soundName": "",
            "type": "LEO",
            "coloredName": "[color=green]Statewide Frequency[/color]",
            "talkEnforcement": true,
            "talkAround": false,
            "scannable": true,
            "encrypted": false,
            "permission": 1
        },
        {
            "id": 2,
            "name": "LS Frequency",
            "soundName": "",
            "type": "LEO",
            "coloredName": "[color=cyan]LS Frequency[/color]",
            "talkEnforcement": true,
            "talkAround": false,
            "scannable": true,
            "encrypted": false,
            "permission": 1
        },
        {
            "id": 3,
            "name": "BC Frequency",
            "soundName": "",
            "type": "LEO",
            "coloredName": "[color=cyan]BC Frequency[/color]",
            "talkEnforcement": true,
            "talkAround": false,
            "scannable": true,
            "encrypted": false,
            "permission": 1
        },
        {
            "id": 4,
            "name": "Encrypted",
            "soundName": "",
            "type": "LEO",
            "coloredName": "[color=cyan]Encrypted[/color]",
            "talkEnforcement": true,
            "talkAround": false,
            "scannable": true,
            "encrypted": true,
            "permission": 1
        },
        {
            "id": 5,
            "name": "Fire Ops",
            "soundName": "",
            "type": "LEO",
            "coloredName": "[color=yellow]Fire Ops[/color]",
            "talkEnforcement": true,
            "talkAround": false,
            "scannable": true,
            "encrypted": false,
            "permission": 1
        },
        {
            "id": 6,
            "name": "CHC Frequency",
            "soundName": "",
            "type": "LEO",
            "coloredName": "[color=orange]CHC Frequency[/color]",
            "talkEnforcement": true,
            "talkAround": false,
            "scannable": true,
            "encrypted": false,
            "permission": 1
        },
        {
            "id": 7,
            "name": "Tac 1",
            "soundName": "",
            "type": "LEO",
            "coloredName": "[color=purple]Tac 1[/color]",
            "talkEnforcement": true,
            "talkAround": false,
            "scannable": true,
            "encrypted": true,
            "permission": 1
        },
        {
            "id": 8,
            "name": "Tac 2",
            "soundName": "",
            "type": "LEO",
            "coloredName": "[color=purple]Tac 2[/color]",
            "talkEnforcement": true,
            "talkAround": false,
            "scannable": true,
            "encrypted": true,
            "permission": 1
        },
        {
            "id": 9,
            "name": "Private 1",
            "soundName": "",
            "type": "LEO",
            "coloredName": "[color=red]Private 1[/color]",
            "talkEnforcement": true,
            "talkAround": false,
            "scannable": false,
            "encrypted": true,
            "permission": 1
        },
        {
            "id": 10,
            "name": "Private 2",
            "soundName": "",
            "type": "LEO",
            "coloredName": "[color=red]Private 2[/color]",
            "talkEnforcement": true,
            "talkAround": false,
            "scannable": false,
            "encrypted": true,
            "permission": 1
        }
    ],
    "time_settings": {
        "emergencyOverridePeriod": 10,
        "emergencyCooldown": 30,
        "emergencyOtherCooldown": 20,
        "dispatchToneCooldown": 15,
        "radioStunCooldown": 5,
        "radioPingCooldown": 10,
        "911Cooldown": 30,
        "commandStunPeriod": 300,
        "toneWaitTalkPeriod": 5
    },
    "permissions": {
        "permBasic": {
            "serverGroupList": [""]
        },
        "permExtra": {
            "serverGroupList": [""]
        },
        "permSit": {
            "serverGroupList": ["456"]
        },
        "permStaff": {
            "serverGroupList": ["457"]
        },
        "permSenior": {
            "serverGroupList": ["458"]
        },
        "permAdmin": {
            "serverGroupList": ["460"]
        },
        "permSuper": {
            "serverGroupList": ["461", "462"]
        }
    }
}
