{
    "pluginStatus": true,
    "isPaid": true,
    "communityName": "Epicenter RP",
    "features": {
        "inGameInterface": true,
        "rangeSimulation": true,
        "emergencyHotline": false
    },
    "talkAroundRange": 1500,
    "betaServerGroups": [""],
    "dispatchServerGroups": [""],
    "dispatchAdvancedServerGroups": [],
    "dispatchNameTags": [
        "(P)",
        "(S)",
        "(T)",
        "(FIRE)",
        "(QA)",
        "(EVAL)",
        "[P]",
        "[S]",
        "[T]",
        "[FIRE]",
        "[QA]",
        "[EVAL]"
    ],
    "civilianServerGroups": [""],
    "civChannels": [0],
    "radioSystems": [6],
    "rtoChannels": [2],
    "radioChannels": [
        {
            "id": 1,
            "name": "Law Enforcement",
            "soundName": "",
            "type": "LEO",
            "coloredName": "[color=green]Law Enforcement[/color]",
            "talkEnforcement": true,
            "talkAround": false,
            "scannable": true,
            "encrypted": false,
            "permission": 1
        },
        {
            "id": 2,
            "name": "Fire/EMS",
            "soundName": "",
            "type": "LEO",
            "coloredName": "[color=yellow]Fire/EMS[/color]",
            "talkEnforcement": true,
            "talkAround": false,
            "scannable": true,
            "encrypted": false,
            "permission": 1
        },
        {
            "id": 3,
            "name": "Misc",
            "soundName": "",
            "type": "LEO",
            "coloredName": "[color=brown]Misc[/color]",
            "talkEnforcement": true,
            "talkAround": false,
            "scannable": true,
            "encrypted": false,
            "permission": 1
        },
        {
            "id": 4,
            "name": "Tac 1",
            "soundName": "",
            "type": "LEO",
            "coloredName": "[color=purple]Tac 1[/color]",
            "talkEnforcement": true,
            "talkAround": false,
            "scannable": true,
            "encrypted": true,
            "permission": 1
        },
        {
            "id": 5,
            "name": "Tac 2",
            "soundName": "",
            "type": "LEO",
            "coloredName": "[color=purple]Tac 2[/color]",
            "talkEnforcement": true,
            "talkAround": false,
            "scannable": true,
            "encrypted": true,
            "permission": 1
        },
        {
            "id": 6,
            "name": "Tac 3",
            "soundName": "",
            "type": "LEO",
            "coloredName": "[color=purple]Tac 3[/color]",
            "talkEnforcement": true,
            "talkAround": false,
            "scannable": true,
            "encrypted": true,
            "permission": 1
        },
        {
            "id": 7,
            "name": "Car/Car 1",
            "soundName": "",
            "type": "LEO",
            "coloredName": "[color=grey]Car/Car 1[/color]",
            "talkEnforcement": true,
            "talkAround": true,
            "scannable": true,
            "encrypted": false,
            "permission": 1
        },
        {
            "id": 8,
            "name": "Car/Car 2",
            "soundName": "",
            "type": "LEO",
            "coloredName": "[color=grey]Car/Car 2[/color]",
            "talkEnforcement": true,
            "talkAround": true,
            "scannable": true,
            "encrypted": false,
            "permission": 1
        },
        {
            "id": 9,
            "name": "Car/Car 3",
            "soundName": "",
            "type": "LEO",
            "coloredName": "[color=grey]Car/Car 3[/color]",
            "talkEnforcement": true,
            "talkAround": true,
            "scannable": true,
            "encrypted": false,
            "permission": 1
        }
    ],
    "time_settings": {
        "emergencyOverridePeriod": 10,
        "emergencyCooldown": 30,
        "emergencyOtherCooldown": 20,
        "dispatchToneCooldown": 15,
        "radioStunCooldown": 5,
        "radioPingCooldown": 10,
        "911Cooldown": 30,
        "commandStunPeriod": 300,
        "toneWaitTalkPeriod": 5
    },
    "permissions": {
        "permBasic": {
            "serverGroupList": [""]
        },
        "permExtra": {
            "serverGroupList": [""]
        },
        "permSit": {
            "serverGroupList": [""]
        },
        "permStaff": {
            "serverGroupList": ["10"]
        },
        "permSenior": {
            "serverGroupList": [""]
        },
        "permAdmin": {
            "serverGroupList": ["5"]
        },
        "permSuper": {
            "serverGroupList": ["2"]
        }
    }
}
